<Properties StartupConfiguration="{5173D903-5FDF-F1A8-033A-7EFD9E51B17E}|">
  <MonoDevelop.Ide.Workbench ActiveDocument="Assets/Scripts/RocketBehavior.cs">
    <Files>
      <File FileName="Assets/Scripts/RocketBehavior.cs" Line="109" Column="26" />
    </Files>
    <Pads>
      <Pad Id="ProjectPad">
        <State name="__root__">
          <Node name="Rocket Launch" expanded="True">
            <Node name="Assets" expanded="True">
              <Node name="Scripts" expanded="True">
                <Node name="RocketBehavior.cs" selected="True" />
              </Node>
            </Node>
          </Node>
        </State>
      </Pad>
    </Pads>
  </MonoDevelop.Ide.Workbench>
  <MonoDevelop.Ide.DebuggingService.PinnedWatches />
  <MonoDevelop.Ide.Workspace ActiveConfiguration="Debug" />
  <MonoDevelop.Ide.ItemProperties.Assembly-CSharp PreferredExecutionTarget="ac82ec51-99f8-420f-a146-1377bf5130e6" />
  <MonoDevelop.Ide.DebuggingService.Breakpoints>
    <BreakpointStore>
      <Breakpoint file="/Users/koniashovivan/Documents/GitHub/RocketLaunch-Learning-Project/Rocket Launch/Assets/Scripts/RocketBehavior.cs" relfile="Assets/Scripts/RocketBehavior.cs" line="101" column="1" />
    </BreakpointStore>
  </MonoDevelop.Ide.DebuggingService.Breakpoints>
  <MultiItemStartupConfigurations />
</Properties>